{
  "description": "Attacks made while stealthed and for 6 seconds after breaking stealth cause an additional 10% damage. In the Rogue Talents category. A spell.",
  "fetched_at": "2026-05-24T09:14:49+00:00",
  "name": "Master of Subtlety",
  "normalized_requirements": [],
  "normalized_sources": [],
  "page_type": "spell",
  "parser_version": "wowhead-scraper-0.6.0",
  "related_tables": {
    "created-by": [],
    "recipes": [],
    "reward-from-q": [],
    "sold-by": [],
    "taught-by-item": [],
    "taught-by-npc": [],
    "taught-by-spell": [],
    "trained-by": []
  },
  "spell_id": 31223,
  "url": "https://www.wowhead.com/tbc/spell=31223/master-of-subtlety"
}
