{
  "description": "Burns the enemy for 332 Fire damage and then an additional 615 Fire damage over 15 sec. In the Destruction Abilities category. Requires Warlock.",
  "fetched_at": "2026-05-24T09:17:55+00:00",
  "name": "Immolate",
  "normalized_requirements": [],
  "normalized_sources": [],
  "page_type": "spell",
  "parser_version": "wowhead-scraper-0.7.0",
  "related_tables": {
    "created-by": [],
    "recipes": [],
    "reward-from-q": [],
    "sold-by": [],
    "taught-by-item": [],
    "taught-by-npc": [],
    "taught-by-spell": [],
    "trained-by": []
  },
  "spell_id": 27215,
  "url": "https://www.wowhead.com/tbc/spell=27215"
}
