{
  "description": "Increases melee, ranged and spell haste rating on nearby party members by 80. Lasts 30 sec. Added in World of Warcraft: The Burning Crusade.",
  "fetched_at": "2026-05-24T08:51:59+00:00",
  "name": "Drums of Battle",
  "normalized_requirements": [],
  "normalized_sources": [],
  "page_type": "spell",
  "parser_version": "wowhead-scraper-0.7.0",
  "related_tables": {
    "created-by": [],
    "recipes": [],
    "reward-from-q": [],
    "sold-by": [],
    "taught-by-item": [],
    "taught-by-npc": [],
    "taught-by-spell": [],
    "trained-by": []
  },
  "spell_id": 35476,
  "url": "https://www.wowhead.com/tbc/spell=35476"
}
