{
  "fetched_at": "2026-05-24T04:24:50+00:00",
  "page_type": "guide",
  "parser_version": "wowhead-scraper-0.4.0",
  "tables": [
    {
      "data_family": "bis_lists",
      "heading": "Best in Slot Head Armor for Feral Druid Tank in TBC Classic Phase 5",
      "rows": [
        {
          "cells": [
            "BiS",
            "Mask of the Fury Hunter",
            "Vendor: Yrma - Requires Duplicitous Guise + 1 Sunmote - Kil'jaeden (Sunwell Plateau)"
          ],
          "entities": [
            {
              "id": 34404,
              "name": "Mask of the Fury Hunter",
              "type": "item",
              "url": "https://www.wowhead.com/tbc/item=34404/mask-of-the-fury-hunter"
            },
            {
              "id": 34244,
              "name": "Duplicitous Guise",
              "type": "item",
              "url": "https://www.wowhead.com/tbc/item=34244/duplicitous-guise"
            },
            {
              "id": 34664,
              "name": "Sunmote",
              "type": "item",
              "url": "https://www.wowhead.com/tbc/item=34664/sunmote"
            }
          ],
          "entity_id": 34404,
          "entity_name": "Mask of the Fury Hunter",
          "entity_type": "item",
          "entity_url": "https://www.wowhead.com/tbc/item=34404/mask-of-the-fury-hunter",
          "item_id": 34404,
          "item_name": "Mask of the Fury Hunter",
          "item_url": "https://www.wowhead.com/tbc/item=34404/mask-of-the-fury-hunter",
          "rank_label": "BiS",
          "source_links": [
            {
              "href": "https://www.wowhead.com/tbc/npc=25977/yrma",
              "text": "Yrma"
            },
            {
              "href": "https://www.wowhead.com/tbc/item=34244/duplicitous-guise",
              "text": "Duplicitous Guise"
            },
            {
              "href": "https://www.wowhead.com/tbc/item=34664/sunmote",
              "text": "Sunmote"
            },
            {
              "href": "https://www.wowhead.com/tbc/npc=25315/kiljaeden",
              "text": "Kil'jaeden"
            }
          ],
          "source_text": "Vendor: Yrma - Requires Duplicitous Guise + 1 Sunmote - Kil'jaeden (Sunwell Plateau)"
        },
        {
          "cells": [
            "Alternative",
            "Duplicitous Guise",
            "Drop: Kil'jaeden (Sunwell Plateau)"
          ],
          "entities": [
            {
              "id": 34244,
              "name": "Duplicitous Guise",
              "type": "item",
              "url": "https://www.wowhead.com/tbc/item=34244/duplicitous-guise"
            }
          ],
          "entity_id": 34244,
          "entity_name": "Duplicitous Guise",
          "entity_type": "item",
          "entity_url": "https://www.wowhead.com/tbc/item=34244/duplicitous-guise",
          "item_id": 34244,
          "item_name": "Duplicitous Guise",
          "item_url": "https://www.wowhead.com/tbc/item=34244/duplicitous-guise",
          "rank_label": "Alternative",
          "source_links": [
            {
              "href": "https://www.wowhead.com/tbc/npc=25315/kiljaeden",
              "text": "Kil'jaeden"
            }
          ],
          "source_text": "Drop: Kil'jaeden (Sunwell Plateau)"
        },
        {
          "cells": [
            "Alternative (Mit Skewed)",
            "Thunderheart Cover",
            "Drop: Helm of the Forgotten Vanquisher - Archimonde (Hyjal Summit)"
          ],
          "entities": [
            {
              "id": 31039,
              "name": "Thunderheart Cover",
              "type": "item",
              "url": "https://www.wowhead.com/tbc/item=31039/thunderheart-cover"
            }
          ],
          "entity_id": 31039,
          "entity_name": "Thunderheart Cover",
          "entity_type": "item",
          "entity_url": "https://www.wowhead.com/tbc/item=31039/thunderheart-cover",
          "item_id": 31039,
          "item_name": "Thunderheart Cover",
          "item_url": "https://www.wowhead.com/tbc/item=31039/thunderheart-cover",
          "rank_label": "Alternative (Mit Skewed)",
          "source_links": [
            {
              "href": "https://www.wowhead.com/tbc/npc=17968/archimonde",
              "text": "Archimonde"
            }
          ],
          "source_text": "Drop: Helm of the Forgotten Vanquisher - Archimonde (Hyjal Summit)"
        },
        {
          "cells": [
            "Alternative (Threat Skewed)",
            "Brutal Gladiator's Dragonhide Helm",
            "1875 , 1700 personal rating"
          ],
          "entities": [
            {
              "id": 34999,
              "name": "Brutal Gladiator's Dragonhide Helm",
              "type": "item",
              "url": "https://www.wowhead.com/tbc/item=34999/brutal-gladiators-dragonhide-helm"
            }
          ],
          "entity_id": 34999,
          "entity_name": "Brutal Gladiator's Dragonhide Helm",
          "entity_type": "item",
          "entity_url": "https://www.wowhead.com/tbc/item=34999/brutal-gladiators-dragonhide-helm",
          "item_id": 34999,
          "item_name": "Brutal Gladiator's Dragonhide Helm",
          "item_url": "https://www.wowhead.com/tbc/item=34999/brutal-gladiators-dragonhide-helm",
          "rank_label": "Alternative (Threat Skewed)",
          "source_links": [
            {
              "href": "https://www.wowhead.com/tbc/currency=1900",
              "text": ""
            }
          ],
          "source_text": "1875 , 1700 personal rating"
        }
      ],
      "slot": "Head"
    },
    {
      "data_family": "bis_lists",
      "heading": "Best in Slot Shoulder Armor for Feral Druid Tank in TBC Classic Phase 5",
      "rows": [
        {
          "cells": [
            "Best Mit Skewed",
            "Demontooth Shoulderpads",
            "Vendor: Yrma - Requires Shoulderpads of Vehemence + 1 Sunmote - Lady Sacrolash (Sunwell Plateau)"
          ],
          "entities": [
            {
              "id": 34392,
              "name": "Demontooth Shoulderpads",
              "type": "item",
              "url": "https://www.wowhead.com/tbc/item=34392/demontooth-shoulderpads"
            },
            {
              "id": 34195,
              "name": "Shoulderpads of Vehemence",
              "type": "item",
              "url": "https://www.wowhead.com/tbc/item=34195/shoulderpads-of-vehemence"
            },
            {
              "id": 34664,
              "name": "Sunmote",
              "type": "item",
              "url": "https://www.wowhead.com/tbc/item=34664/sunmote"
            }
          ],
          "entity_id": 34392,
          "entity_name": "Demontooth Shoulderpads",
          "entity_type": "item",
          "entity_url": "https://www.wowhead.com/tbc/item=34392/demontooth-shoulderpads",
          "item_id": 34392,
          "item_name": "Demontooth Shoulderpads",
          "item_url": "https://www.wowhead.com/tbc/item=34392/demontooth-shoulderpads",
          "rank_label": "Best Mit Skewed",
          "source_links": [
            {
              "href": "https://www.wowhead.com/tbc/npc=25977/yrma",
              "text": "Yrma"
            },
            {
              "href": "https://www.wowhead.com/tbc/item=34195/shoulderpads-of-vehemence",
              "text": "Shoulderpads of Vehemence"
            },
            {
              "href": "https://www.wowhead.com/tbc/item=34664/sunmote",
              "text": "Sunmote"
            },
            {
              "href": "https://www.wowhead.com/tbc/npc=25165/lady-sacrolash",
              "text": "Lady Sacrolash"
            }
          ],
          "source_text": "Vendor: Yrma - Requires Shoulderpads of Vehemence + 1 Sunmote - Lady Sacrolash (Sunwell Plateau)"
        },
        {
          "cells": [
            "Best Threat Skewed (with 4pT6 Bonus)",
            "Thunderheart Pauldrons",
            "Drop: Pauldrons of the Forgotten Vanquisher - Mother Shahraz (Black Temple)"
          ],
          "entities": [
            {
              "id": 31048,
              "name": "Thunderheart Pauldrons",
              "type": "item",
              "url": "https://www.wowhead.com/tbc/item=31048/thunderheart-pauldrons"
            }
          ],
          "entity_id": 31048,
          "entity_name": "Thunderheart Pauldrons",
          "entity_type": "item",
          "entity_url": "https://www.wowhead.com/tbc/item=31048/thunderheart-pauldrons",
          "item_id": 31048,
          "item_name": "Thunderheart Pauldrons",
          "item_url": "https://www.wowhead.com/tbc/item=31048/thunderheart-pauldrons",
          "rank_label": "Best Threat Skewed (with 4pT6 Bonus)",
          "source_links": [
            {
              "href": "https://www.wowhead.com/tbc/npc=22947/mother-shahraz",
              "text": "Mother Shahraz"
            }
          ],
          "source_text": "Drop: Pauldrons of the Forgotten Vanquisher - Mother Shahraz (Black Temple)"
        },
        {
          "cells": [
            "Alternative",
            "Brutal Gladiator's Dragonhide Spaulders",
            "1500 , 2200 personal rating"
          ],
          "entities": [
            {
              "id": 35001,
              "name": "Brutal Gladiator's Dragonhide Spaulders",
              "type": "item",
              "url": "https://www.wowhead.com/tbc/item=35001/brutal-gladiators-dragonhide-spaulders"
            }
          ],
          "entity_id": 35001,
          "entity_name": "Brutal Gladiator's Dragonhide Spaulders",
          "entity_type": "item",
          "entity_url": "https://www.wowhead.com/tbc/item=35001/brutal-gladiators-dragonhide-spaulders",
          "item_id": 35001,
          "item_name": "Brutal Gladiator's Dragonhide Spaulders",
          "item_url": "https://www.wowhead.com/tbc/item=35001/brutal-gladiators-dragonhide-spaulders",
          "rank_label": "Alternative",
          "source_links": [
            {
              "href": "https://www.wowhead.com/tbc/currency=1900",
              "text": ""
            }
          ],
          "source_text": "1500 , 2200 personal rating"
        },
        {
          "cells": [
            "Alternative",
            "Vengeful Gladiator's Dragonhide Spaulders",
            "750"
          ],
          "entities": [
            {
              "id": 33674,
              "name": "Vengeful Gladiator's Dragonhide Spaulders",
              "type": "item",
              "url": "https://www.wowhead.com/tbc/item=33674/vengeful-gladiators-dragonhide-spaulders"
            }
          ],
          "entity_id": 33674,
          "entity_name": "Vengeful Gladiator's Dragonhide Spaulders",
          "entity_type": "item",
          "entity_url": "https://www.wowhead.com/tbc/item=33674/vengeful-gladiators-dragonhide-spaulders",
          "item_id": 33674,
          "item_name": "Vengeful Gladiator's Dragonhide Spaulders",
          "item_url": "https://www.wowhead.com/tbc/item=33674/vengeful-gladiators-dragonhide-spaulders",
          "rank_label": "Alternative",
          "source_links": [
            {
              "href": "https://www.wowhead.com/tbc/currency=1900",
              "text": ""
            }
          ],
          "source_text": "750"
        }
      ],
      "slot": "Shoulder"
    },
    {
      "data_family": "bis_lists",
      "heading": "Best in Slot Back Armor for Feral Druid Tank in TBC Classic Phase 5",
      "rows": [
        {
          "cells": [
            "BiS",
            "Crimson Paragon's Cover",
            "Drop: Grand Warlock Alythess / Lady Sacrolash (Sunwell Plateau)"
          ],
          "entities": [
            {
              "id": 34190,
              "name": "Crimson Paragon's Cover",
              "type": "item",
              "url": "https://www.wowhead.com/tbc/item=34190/crimson-paragons-cover"
            }
          ],
          "entity_id": 34190,
          "entity_name": "Crimson Paragon's Cover",
          "entity_type": "item",
          "entity_url": "https://www.wowhead.com/tbc/item=34190/crimson-paragons-cover",
          "item_id": 34190,
          "item_name": "Crimson Paragon's Cover",
          "item_url": "https://www.wowhead.com/tbc/item=34190/crimson-paragons-cover",
          "rank_label": "BiS",
          "source_links": [
            {
              "href": "https://www.wowhead.com/tbc/npc=25166/grand-warlock-alythess",
              "text": "Grand Warlock Alythess"
            },
            {
              "href": "https://www.wowhead.com/tbc/npc=25165/lady-sacrolash",
              "text": "Lady Sacrolash"
            }
          ],
          "source_text": "Drop: Grand Warlock Alythess / Lady Sacrolash (Sunwell Plateau)"
        },
        {
          "cells": [
            "Alternative",
            "Cloak of Unforgivable Sin",
            "Drop: Kil'jaeden (Sunwell Plateau)"
          ],
          "entities": [
            {
              "id": 34241,
              "name": "Cloak of Unforgivable Sin",
              "type": "item",
              "url": "https://www.wowhead.com/tbc/item=34241/cloak-of-unforgivable-sin"
            }
          ],
          "entity_id": 34241,
          "entity_name": "Cloak of Unforgivable Sin",
          "entity_type": "item",
          "entity_url": "https://www.wowhead.com/tbc/item=34241/cloak-of-unforgivable-sin",
          "item_id": 34241,
          "item_name": "Cloak of Unforgivable Sin",
          "item_url": "https://www.wowhead.com/tbc/item=34241/cloak-of-unforgivable-sin",
          "rank_label": "Alternative",
          "source_links": [
            {
              "href": "https://www.wowhead.com/tbc/npc=25315/kiljaeden",
              "text": "Kil'jaeden"
            }
          ],
          "source_text": "Drop: Kil'jaeden (Sunwell Plateau)"
        },
        {
          "cells": [
            "Alternative",
            "Pepe's Shroud of Pacification",
            "Drop: Hyjal Summit Trash Mobs"
          ],
          "entities": [
            {
              "id": 34010,
              "name": "Pepe's Shroud of Pacification",
              "type": "item",
              "url": "https://www.wowhead.com/tbc/item=34010/pepes-shroud-of-pacification"
            }
          ],
          "entity_id": 34010,
          "entity_name": "Pepe's Shroud of Pacification",
          "entity_type": "item",
          "entity_url": "https://www.wowhead.com/tbc/item=34010/pepes-shroud-of-pacification",
          "item_id": 34010,
          "item_name": "Pepe's Shroud of Pacification",
          "item_url": "https://www.wowhead.com/tbc/item=34010/pepes-shroud-of-pacification",
          "rank_label": "Alternative",
          "source_links": [
            {
              "href": "https://www.wowhead.com/tbc/zone=3606/hyjal-summit",
              "text": "Hyjal Summit"
            }
          ],
          "source_text": "Drop: Hyjal Summit Trash Mobs"
        }
      ],
      "slot": "Back"
    },
    {
      "data_family": "bis_lists",
      "heading": "Best in Slot Chest Armor for Feral Druid Tank in TBC Classic Phase 5",
      "rows": [
        {
          "cells": [
            "BiS",
            "Harness of Carnal Instinct",
            "Drop: M'uru (Sunwell Plateau)"
          ],
          "entities": [
            {
              "id": 34211,
              "name": "Harness of Carnal Instinct",
              "type": "item",
              "url": "https://www.wowhead.com/tbc/item=34211/harness-of-carnal-instinct"
            }
          ],
          "entity_id": 34211,
          "entity_name": "Harness of Carnal Instinct",
          "entity_type": "item",
          "entity_url": "https://www.wowhead.com/tbc/item=34211/harness-of-carnal-instinct",
          "item_id": 34211,
          "item_name": "Harness of Carnal Instinct",
          "item_url": "https://www.wowhead.com/tbc/item=34211/harness-of-carnal-instinct",
          "rank_label": "BiS",
          "source_links": [
            {
              "href": "https://www.wowhead.com/tbc/npc=25741/muru",
              "text": "M'uru"
            }
          ],
          "source_text": "Drop: M'uru (Sunwell Plateau)"
        },
        {
          "cells": [
            "Mit Skewed Alternative",
            "Thunderheart Chestguard",
            "Drop: Chestguard of the Forgotten Vanquisher - Illidan Stormrage (Black Temple)"
          ],
          "entities": [
            {
              "id": 31042,
              "name": "Thunderheart Chestguard",
              "type": "item",
              "url": "https://www.wowhead.com/tbc/item=31042/thunderheart-chestguard"
            }
          ],
          "entity_id": 31042,
          "entity_name": "Thunderheart Chestguard",
          "entity_type": "item",
          "entity_url": "https://www.wowhead.com/tbc/item=31042/thunderheart-chestguard",
          "item_id": 31042,
          "item_name": "Thunderheart Chestguard",
          "item_url": "https://www.wowhead.com/tbc/item=31042/thunderheart-chestguard",
          "rank_label": "Mit Skewed Alternative",
          "source_links": [
            {
              "href": "https://www.wowhead.com/tbc/npc=22917/illidan-stormrage",
              "text": "Illidan Stormrage"
            }
          ],
          "source_text": "Drop: Chestguard of the Forgotten Vanquisher - Illidan Stormrage (Black Temple)"
        },
        {
          "cells": [
            "Threat Skewed Alternative",
            "Carapace of Sun and Shadow",
            "Profession: Leatherworking (BoP)"
          ],
          "entities": [
            {
              "id": 34369,
              "name": "Carapace of Sun and Shadow",
              "type": "item",
              "url": "https://www.wowhead.com/tbc/item=34369/carapace-of-sun-and-shadow"
            }
          ],
          "entity_id": 34369,
          "entity_name": "Carapace of Sun and Shadow",
          "entity_type": "item",
          "entity_url": "https://www.wowhead.com/tbc/item=34369/carapace-of-sun-and-shadow",
          "item_id": 34369,
          "item_name": "Carapace of Sun and Shadow",
          "item_url": "https://www.wowhead.com/tbc/item=34369/carapace-of-sun-and-shadow",
          "rank_label": "Threat Skewed Alternative",
          "source_links": [],
          "source_text": "Profession: Leatherworking (BoP)"
        },
        {
          "cells": [
            "Mit Skewed Alternative",
            "Brutal Gladiator's Dragonhide Tunic",
            "1875 , 1600 personal rating"
          ],
          "entities": [
            {
              "id": 35002,
              "name": "Brutal Gladiator's Dragonhide Tunic",
              "type": "item",
              "url": "https://www.wowhead.com/tbc/item=35002/brutal-gladiators-dragonhide-tunic"
            }
          ],
          "entity_id": 35002,
          "entity_name": "Brutal Gladiator's Dragonhide Tunic",
          "entity_type": "item",
          "entity_url": "https://www.wowhead.com/tbc/item=35002/brutal-gladiators-dragonhide-tunic",
          "item_id": 35002,
          "item_name": "Brutal Gladiator's Dragonhide Tunic",
          "item_url": "https://www.wowhead.com/tbc/item=35002/brutal-gladiators-dragonhide-tunic",
          "rank_label": "Mit Skewed Alternative",
          "source_links": [
            {
              "href": "https://www.wowhead.com/tbc/currency=1900",
              "text": ""
            }
          ],
          "source_text": "1875 , 1600 personal rating"
        }
      ],
      "slot": "Chest"
    },
    {
      "data_family": "bis_lists",
      "heading": "Best in Slot Chest Armor for Feral Druid Tank in TBC Classic Phase 5",
      "rows": [
        {
          "cells": [
            "Threat Skewed Alternative",
            "Bladed Chaos Tunic",
            "Vendor: Yrma - Harness of Carnal Instinct + 1 Sunmote - M'uru (Sunwell Plateau)"
          ],
          "entities": [
            {
              "id": 34397,
              "name": "Bladed Chaos Tunic",
              "type": "item",
              "url": "https://www.wowhead.com/tbc/item=34397/bladed-chaos-tunic"
            },
            {
              "id": 34211,
              "name": "Harness of Carnal Instinct",
              "type": "item",
              "url": "https://www.wowhead.com/tbc/item=34211/harness-of-carnal-instinct"
            },
            {
              "id": 34664,
              "name": "Sunmote",
              "type": "item",
              "url": "https://www.wowhead.com/tbc/item=34664/sunmote"
            }
          ],
          "entity_id": 34397,
          "entity_name": "Bladed Chaos Tunic",
          "entity_type": "item",
          "entity_url": "https://www.wowhead.com/tbc/item=34397/bladed-chaos-tunic",
          "item_id": 34397,
          "item_name": "Bladed Chaos Tunic",
          "item_url": "https://www.wowhead.com/tbc/item=34397/bladed-chaos-tunic",
          "rank_label": "Threat Skewed Alternative",
          "source_links": [
            {
              "href": "https://www.wowhead.com/tbc/npc=25977/yrma",
              "text": "Yrma"
            },
            {
              "href": "https://www.wowhead.com/tbc/item=34211/harness-of-carnal-instinct",
              "text": "Harness of Carnal Instinct"
            },
            {
              "href": "https://www.wowhead.com/tbc/item=34664/sunmote",
              "text": "Sunmote"
            },
            {
              "href": "https://www.wowhead.com/tbc/npc=25741/muru",
              "text": "M'uru"
            }
          ],
          "source_text": "Vendor: Yrma - Harness of Carnal Instinct + 1 Sunmote - M'uru (Sunwell Plateau)"
        },
        {
          "cells": [
            "Mit Skewed Alternative",
            "Embrace of Everlasting Prowess",
            "Vendor: Smith Hauthaa , (100 Badges of Justice)"
          ],
          "entities": [
            {
              "id": 34906,
              "name": "Embrace of Everlasting Prowess",
              "type": "item",
              "url": "https://www.wowhead.com/tbc/item=34906/embrace-of-everlasting-prowess"
            }
          ],
          "entity_id": 34906,
          "entity_name": "Embrace of Everlasting Prowess",
          "entity_type": "item",
          "entity_url": "https://www.wowhead.com/tbc/item=34906/embrace-of-everlasting-prowess",
          "item_id": 34906,
          "item_name": "Embrace of Everlasting Prowess",
          "item_url": "https://www.wowhead.com/tbc/item=34906/embrace-of-everlasting-prowess",
          "rank_label": "Mit Skewed Alternative",
          "source_links": [
            {
              "href": "https://www.wowhead.com/tbc/npc=25046/smith-hauthaa",
              "text": "Smith Hauthaa"
            }
          ],
          "source_text": "Vendor: Smith Hauthaa , (100 Badges of Justice)"
        }
      ],
      "slot": "Chest"
    },
    {
      "data_family": "bis_lists",
      "heading": "Best in Slot Wrist Armor for Feral Druid Tank in TBC Classic Phase 5",
      "rows": [
        {
          "cells": [
            "BiS",
            "Thunderheart Wristguards",
            "Drop: Bracers of the Forgotten Vanquisher - Kalecgos / Sathrovarr the Corruptor (Sunwell Plateau)"
          ],
          "entities": [
            {
              "id": 34444,
              "name": "Thunderheart Wristguards",
              "type": "item",
              "url": "https://www.wowhead.com/tbc/item=34444/thunderheart-wristguards"
            }
          ],
          "entity_id": 34444,
          "entity_name": "Thunderheart Wristguards",
          "entity_type": "item",
          "entity_url": "https://www.wowhead.com/tbc/item=34444/thunderheart-wristguards",
          "item_id": 34444,
          "item_name": "Thunderheart Wristguards",
          "item_url": "https://www.wowhead.com/tbc/item=34444/thunderheart-wristguards",
          "rank_label": "BiS",
          "source_links": [
            {
              "href": "https://www.wowhead.com/tbc/npc=24850/kalecgos",
              "text": "Kalecgos"
            },
            {
              "href": "https://www.wowhead.com/tbc/npc=24892/sathrovarr-the-corruptor",
              "text": "Sathrovarr the Corruptor"
            }
          ],
          "source_text": "Drop: Bracers of the Forgotten Vanquisher - Kalecgos / Sathrovarr the Corruptor (Sunwell Plateau)"
        },
        {
          "cells": [
            "Mit Skewed Alternative",
            "Guardian's Leather Bracers",
            "11,794 , 10 Warsong Gulch Mark of Honor , 1575 personal rating"
          ],
          "entities": [
            {
              "id": 35171,
              "name": "Guardian's Leather Bracers",
              "type": "item",
              "url": "https://www.wowhead.com/tbc/item=35171/guardians-leather-bracers"
            },
            {
              "id": 20558,
              "name": "Warsong Gulch Mark of Honor",
              "type": "item",
              "url": "https://www.wowhead.com/tbc/item=20558/warsong-gulch-mark-of-honor"
            }
          ],
          "entity_id": 35171,
          "entity_name": "Guardian's Leather Bracers",
          "entity_type": "item",
          "entity_url": "https://www.wowhead.com/tbc/item=35171/guardians-leather-bracers",
          "item_id": 35171,
          "item_name": "Guardian's Leather Bracers",
          "item_url": "https://www.wowhead.com/tbc/item=35171/guardians-leather-bracers",
          "rank_label": "Mit Skewed Alternative",
          "source_links": [
            {
              "href": "https://www.wowhead.com/tbc/currency=1901",
              "text": ""
            },
            {
              "href": "https://www.wowhead.com/tbc/item=20558/warsong-gulch-mark-of-honor",
              "text": "Warsong Gulch Mark of Honor"
            }
          ],
          "source_text": "11,794 , 10 Warsong Gulch Mark of Honor , 1575 personal rating"
        },
        {
          "cells": [
            "Threat Skewed Alternative",
            "Guardian's Dragonhide Bracers",
            "11,794 , 10 Warsong Gulch Mark of Honor , 1575 personal rating"
          ],
          "entities": [
            {
              "id": 35167,
              "name": "Guardian's Dragonhide Bracers",
              "type": "item",
              "url": "https://www.wowhead.com/tbc/item=35167/guardians-dragonhide-bracers"
            },
            {
              "id": 20558,
              "name": "Warsong Gulch Mark of Honor",
              "type": "item",
              "url": "https://www.wowhead.com/tbc/item=20558/warsong-gulch-mark-of-honor"
            }
          ],
          "entity_id": 35167,
          "entity_name": "Guardian's Dragonhide Bracers",
          "entity_type": "item",
          "entity_url": "https://www.wowhead.com/tbc/item=35167/guardians-dragonhide-bracers",
          "item_id": 35167,
          "item_name": "Guardian's Dragonhide Bracers",
          "item_url": "https://www.wowhead.com/tbc/item=35167/guardians-dragonhide-bracers",
          "rank_label": "Threat Skewed Alternative",
          "source_links": [
            {
              "href": "https://www.wowhead.com/tbc/currency=1901",
              "text": ""
            },
            {
              "href": "https://www.wowhead.com/tbc/item=20558/warsong-gulch-mark-of-honor",
              "text": "Warsong Gulch Mark of Honor"
            }
          ],
          "source_text": "11,794 , 10 Warsong Gulch Mark of Honor , 1575 personal rating"
        },
        {
          "cells": [
            "Alternative",
            "Band of the Swift Paw",
            "Vendor: G'eras (35 Badges of Justice)"
          ],
          "entities": [
            {
              "id": 33580,
              "name": "Band of the Swift Paw",
              "type": "item",
              "url": "https://www.wowhead.com/tbc/item=33580/band-of-the-swift-paw"
            }
          ],
          "entity_id": 33580,
          "entity_name": "Band of the Swift Paw",
          "entity_type": "item",
          "entity_url": "https://www.wowhead.com/tbc/item=33580/band-of-the-swift-paw",
          "item_id": 33580,
          "item_name": "Band of the Swift Paw",
          "item_url": "https://www.wowhead.com/tbc/item=33580/band-of-the-swift-paw",
          "rank_label": "Alternative",
          "source_links": [
            {
              "href": "https://www.wowhead.com/tbc/npc=18525/geras",
              "text": "G'eras"
            }
          ],
          "source_text": "Vendor: G'eras (35 Badges of Justice)"
        }
      ],
      "slot": "Wrist"
    },
    {
      "data_family": "bis_lists",
      "heading": "Best in Slot Hand Armor for Feral Druid Tank in TBC Classic Phase 5",
      "rows": [
        {
          "cells": [
            "BiS",
            "Gloves of the Forest Drifter",
            "Vendor: Yrma - Shadowed Gauntlets of Paroxysm + 1 Sunmote - M'uru (Sunwell Plateau)"
          ],
          "entities": [
            {
              "id": 34408,
              "name": "Gloves of the Forest Drifter",
              "type": "item",
              "url": "https://www.wowhead.com/tbc/item=34408/gloves-of-the-forest-drifter"
            },
            {
              "id": 34234,
              "name": "Shadowed Gauntlets of Paroxysm",
              "type": "item",
              "url": "https://www.wowhead.com/tbc/item=34234/shadowed-gauntlets-of-paroxysm"
            },
            {
              "id": 34664,
              "name": "Sunmote",
              "type": "item",
              "url": "https://www.wowhead.com/tbc/item=34664/sunmote"
            }
          ],
          "entity_id": 34408,
          "entity_name": "Gloves of the Forest Drifter",
          "entity_type": "item",
          "entity_url": "https://www.wowhead.com/tbc/item=34408/gloves-of-the-forest-drifter",
          "item_id": 34408,
          "item_name": "Gloves of the Forest Drifter",
          "item_url": "https://www.wowhead.com/tbc/item=34408/gloves-of-the-forest-drifter",
          "rank_label": "BiS",
          "source_links": [
            {
              "href": "https://www.wowhead.com/tbc/npc=25977/yrma",
              "text": "Yrma"
            },
            {
              "href": "https://www.wowhead.com/tbc/item=34234/shadowed-gauntlets-of-paroxysm",
              "text": "Shadowed Gauntlets of Paroxysm"
            },
            {
              "href": "https://www.wowhead.com/tbc/item=34664/sunmote",
              "text": "Sunmote"
            },
            {
              "href": "https://www.wowhead.com/tbc/npc=25741/muru",
              "text": "M'uru"
            }
          ],
          "source_text": "Vendor: Yrma - Shadowed Gauntlets of Paroxysm + 1 Sunmote - M'uru (Sunwell Plateau)"
        },
        {
          "cells": [
            "Mit Skewed Alternative",
            "Handwraps of the Aggressor",
            "Vendor: Smith Hauthaa , (75 Badges of Justice)"
          ],
          "entities": [
            {
              "id": 34911,
              "name": "Handwraps of the Aggressor",
              "type": "item",
              "url": "https://www.wowhead.com/tbc/item=34911/handwraps-of-the-aggressor"
            }
          ],
          "entity_id": 34911,
          "entity_name": "Handwraps of the Aggressor",
          "entity_type": "item",
          "entity_url": "https://www.wowhead.com/tbc/item=34911/handwraps-of-the-aggressor",
          "item_id": 34911,
          "item_name": "Handwraps of the Aggressor",
          "item_url": "https://www.wowhead.com/tbc/item=34911/handwraps-of-the-aggressor",
          "rank_label": "Mit Skewed Alternative",
          "source_links": [
            {
              "href": "https://www.wowhead.com/tbc/npc=25046/smith-hauthaa",
              "text": "Smith Hauthaa"
            }
          ],
          "source_text": "Vendor: Smith Hauthaa , (75 Badges of Justice)"
        },
        {
          "cells": [
            "Threat Skewed Alternative",
            "Shadowed Gauntlets of Paroxysm",
            "Drop: M'uru (Sunwell Plateau)"
          ],
          "entities": [
            {
              "id": 34234,
              "name": "Shadowed Gauntlets of Paroxysm",
              "type": "item",
              "url": "https://www.wowhead.com/tbc/item=34234/shadowed-gauntlets-of-paroxysm"
            }
          ],
          "entity_id": 34234,
          "entity_name": "Shadowed Gauntlets of Paroxysm",
          "entity_type": "item",
          "entity_url": "https://www.wowhead.com/tbc/item=34234/shadowed-gauntlets-of-paroxysm",
          "item_id": 34234,
          "item_name": "Shadowed Gauntlets of Paroxysm",
          "item_url": "https://www.wowhead.com/tbc/item=34234/shadowed-gauntlets-of-paroxysm",
          "rank_label": "Threat Skewed Alternative",
          "source_links": [
            {
              "href": "https://www.wowhead.com/tbc/npc=25741/muru",
              "text": "M'uru"
            }
          ],
          "source_text": "Drop: M'uru (Sunwell Plateau)"
        },
        {
          "cells": [
            "Mit Skewed Alternative",
            "Thunderheart Gauntlets",
            "Drop: Gloves of the Forgotten Vanquisher - Azgalor (Hyjal Summit)"
          ],
          "entities": [
            {
              "id": 31034,
              "name": "Thunderheart Gauntlets",
              "type": "item",
              "url": "https://www.wowhead.com/tbc/item=31034/thunderheart-gauntlets"
            }
          ],
          "entity_id": 31034,
          "entity_name": "Thunderheart Gauntlets",
          "entity_type": "item",
          "entity_url": "https://www.wowhead.com/tbc/item=31034/thunderheart-gauntlets",
          "item_id": 31034,
          "item_name": "Thunderheart Gauntlets",
          "item_url": "https://www.wowhead.com/tbc/item=31034/thunderheart-gauntlets",
          "rank_label": "Mit Skewed Alternative",
          "source_links": [
            {
              "href": "https://www.wowhead.com/tbc/npc=17842/azgalor",
              "text": "Azgalor"
            }
          ],
          "source_text": "Drop: Gloves of the Forgotten Vanquisher - Azgalor (Hyjal Summit)"
        }
      ],
      "slot": "Hands"
    },
    {
      "data_family": "bis_lists",
      "heading": "Best in Slot Hand Armor for Feral Druid Tank in TBC Classic Phase 5",
      "rows": [
        {
          "cells": [
            "Threat Skewed Alternative",
            "Gloves of Immortal Dusk",
            "Profession: Leatherworking (BoE)"
          ],
          "entities": [
            {
              "id": 34370,
              "name": "Gloves of Immortal Dusk",
              "type": "item",
              "url": "https://www.wowhead.com/tbc/item=34370/gloves-of-immortal-dusk"
            }
          ],
          "entity_id": 34370,
          "entity_name": "Gloves of Immortal Dusk",
          "entity_type": "item",
          "entity_url": "https://www.wowhead.com/tbc/item=34370/gloves-of-immortal-dusk",
          "item_id": 34370,
          "item_name": "Gloves of Immortal Dusk",
          "item_url": "https://www.wowhead.com/tbc/item=34370/gloves-of-immortal-dusk",
          "rank_label": "Threat Skewed Alternative",
          "source_links": [],
          "source_text": "Profession: Leatherworking (BoE)"
        }
      ],
      "slot": "Hands"
    },
    {
      "data_family": "bis_lists",
      "heading": "Best in Slot Waist Armor for Feral Druid Tank in TBC Classic Phase 5",
      "rows": [
        {
          "cells": [
            "Best Mit Skewed",
            "Guardian's Leather Belt",
            "17,850 , 20 Arathi Basin Mark of Honor"
          ],
          "entities": [
            {
              "id": 35156,
              "name": "Guardian's Leather Belt",
              "type": "item",
              "url": "https://www.wowhead.com/tbc/item=35156/guardians-leather-belt"
            },
            {
              "id": 20559,
              "name": "Arathi Basin Mark of Honor",
              "type": "item",
              "url": "https://www.wowhead.com/tbc/item=20559/arathi-basin-mark-of-honor"
            }
          ],
          "entity_id": 35156,
          "entity_name": "Guardian's Leather Belt",
          "entity_type": "item",
          "entity_url": "https://www.wowhead.com/tbc/item=35156/guardians-leather-belt",
          "item_id": 35156,
          "item_name": "Guardian's Leather Belt",
          "item_url": "https://www.wowhead.com/tbc/item=35156/guardians-leather-belt",
          "rank_label": "Best Mit Skewed",
          "source_links": [
            {
              "href": "https://www.wowhead.com/tbc/currency=1901",
              "text": ""
            },
            {
              "href": "https://www.wowhead.com/tbc/item=20559/arathi-basin-mark-of-honor",
              "text": "Arathi Basin Mark of Honor"
            }
          ],
          "source_text": "17,850 , 20 Arathi Basin Mark of Honor"
        },
        {
          "cells": [
            "Best Threat Skewed",
            "Thunderheart Waistguard",
            "Drop: Belt of the Forgotten Vanquisher - Brutallus (Sunwell Plateau)]"
          ],
          "entities": [
            {
              "id": 34556,
              "name": "Thunderheart Waistguard",
              "type": "item",
              "url": "https://www.wowhead.com/tbc/item=34556/thunderheart-waistguard"
            }
          ],
          "entity_id": 34556,
          "entity_name": "Thunderheart Waistguard",
          "entity_type": "item",
          "entity_url": "https://www.wowhead.com/tbc/item=34556/thunderheart-waistguard",
          "item_id": 34556,
          "item_name": "Thunderheart Waistguard",
          "item_url": "https://www.wowhead.com/tbc/item=34556/thunderheart-waistguard",
          "rank_label": "Best Threat Skewed",
          "source_links": [
            {
              "href": "https://www.wowhead.com/tbc/npc=24882/brutallus",
              "text": "Brutallus"
            }
          ],
          "source_text": "Drop: Belt of the Forgotten Vanquisher - Brutallus (Sunwell Plateau)]"
        },
        {
          "cells": [
            "Alternative",
            "Belt of One-Hundred Deaths",
            "Drop: Lady Vashj (Serpentshrine Cavern)"
          ],
          "entities": [
            {
              "id": 30106,
              "name": "Belt of One-Hundred Deaths",
              "type": "item",
              "url": "https://www.wowhead.com/tbc/item=30106/belt-of-one-hundred-deaths"
            }
          ],
          "entity_id": 30106,
          "entity_name": "Belt of One-Hundred Deaths",
          "entity_type": "item",
          "entity_url": "https://www.wowhead.com/tbc/item=30106/belt-of-one-hundred-deaths",
          "item_id": 30106,
          "item_name": "Belt of One-Hundred Deaths",
          "item_url": "https://www.wowhead.com/tbc/item=30106/belt-of-one-hundred-deaths",
          "rank_label": "Alternative",
          "source_links": [
            {
              "href": "https://www.wowhead.com/tbc/npc=21212/lady-vashj",
              "text": "Lady Vashj"
            }
          ],
          "source_text": "Drop: Lady Vashj (Serpentshrine Cavern)"
        },
        {
          "cells": [
            "Alternative",
            "Waistguard of the Great Beast",
            "Vendor: G'eras (60 Badges of Justice)"
          ],
          "entities": [
            {
              "id": 33583,
              "name": "Waistguard of the Great Beast",
              "type": "item",
              "url": "https://www.wowhead.com/tbc/item=33583/waistguard-of-the-great-beast"
            }
          ],
          "entity_id": 33583,
          "entity_name": "Waistguard of the Great Beast",
          "entity_type": "item",
          "entity_url": "https://www.wowhead.com/tbc/item=33583/waistguard-of-the-great-beast",
          "item_id": 33583,
          "item_name": "Waistguard of the Great Beast",
          "item_url": "https://www.wowhead.com/tbc/item=33583/waistguard-of-the-great-beast",
          "rank_label": "Alternative",
          "source_links": [
            {
              "href": "https://www.wowhead.com/tbc/npc=18525/geras",
              "text": "G'eras"
            }
          ],
          "source_text": "Vendor: G'eras (60 Badges of Justice)"
        }
      ],
      "slot": "Waist"
    },
    {
      "data_family": "bis_lists",
      "heading": "Best in Slot Leg Armor for Feral Druid Tank in TBC Classic Phase 5",
      "rows": [
        {
          "cells": [
            "BiS",
            "Leggings of the Immortal Beast",
            "Vendor: Yrma - Leggings of the Immortal Night + 1 Sunmote - Felmyst (Sunwell Plateau)"
          ],
          "entities": [
            {
              "id": 34385,
              "name": "Leggings of the Immortal Beast",
              "type": "item",
              "url": "https://www.wowhead.com/tbc/item=34385/leggings-of-the-immortal-beast"
            },
            {
              "id": 34188,
              "name": "Leggings of the Immortal Night",
              "type": "item",
              "url": "https://www.wowhead.com/tbc/item=34188/leggings-of-the-immortal-night"
            },
            {
              "id": 34664,
              "name": "Sunmote",
              "type": "item",
              "url": "https://www.wowhead.com/tbc/item=34664/sunmote"
            }
          ],
          "entity_id": 34385,
          "entity_name": "Leggings of the Immortal Beast",
          "entity_type": "item",
          "entity_url": "https://www.wowhead.com/tbc/item=34385/leggings-of-the-immortal-beast",
          "item_id": 34385,
          "item_name": "Leggings of the Immortal Beast",
          "item_url": "https://www.wowhead.com/tbc/item=34385/leggings-of-the-immortal-beast",
          "rank_label": "BiS",
          "source_links": [
            {
              "href": "https://www.wowhead.com/tbc/npc=25977/yrma",
              "text": "Yrma"
            },
            {
              "href": "https://www.wowhead.com/tbc/item=34188/leggings-of-the-immortal-night",
              "text": "Leggings of the Immortal Night"
            },
            {
              "href": "https://www.wowhead.com/tbc/item=34664/sunmote",
              "text": "Sunmote"
            },
            {
              "href": "https://www.wowhead.com/tbc/npc=25038/felmyst",
              "text": "Felmyst"
            }
          ],
          "source_text": "Vendor: Yrma - Leggings of the Immortal Night + 1 Sunmote - Felmyst (Sunwell Plateau)"
        },
        {
          "cells": [
            "Mit Skewed Alternative",
            "Tameless Breeches",
            "Vendor: Smith Hauthaa (60 Badges of Justice)"
          ],
          "entities": [
            {
              "id": 34910,
              "name": "Tameless Breeches",
              "type": "item",
              "url": "https://www.wowhead.com/tbc/item=34910/tameless-breeches"
            }
          ],
          "entity_id": 34910,
          "entity_name": "Tameless Breeches",
          "entity_type": "item",
          "entity_url": "https://www.wowhead.com/tbc/item=34910/tameless-breeches",
          "item_id": 34910,
          "item_name": "Tameless Breeches",
          "item_url": "https://www.wowhead.com/tbc/item=34910/tameless-breeches",
          "rank_label": "Mit Skewed Alternative",
          "source_links": [
            {
              "href": "https://www.wowhead.com/tbc/npc=25046/smith-hauthaa",
              "text": "Smith Hauthaa"
            }
          ],
          "source_text": "Vendor: Smith Hauthaa (60 Badges of Justice)"
        },
        {
          "cells": [
            "Threat Skewed Alternative",
            "Leggings of the Immortal Night",
            "Drop: Felmyst (Sunwell Plateau)"
          ],
          "entities": [
            {
              "id": 34188,
              "name": "Leggings of the Immortal Night",
              "type": "item",
              "url": "https://www.wowhead.com/tbc/item=34188/leggings-of-the-immortal-night"
            }
          ],
          "entity_id": 34188,
          "entity_name": "Leggings of the Immortal Night",
          "entity_type": "item",
          "entity_url": "https://www.wowhead.com/tbc/item=34188/leggings-of-the-immortal-night",
          "item_id": 34188,
          "item_name": "Leggings of the Immortal Night",
          "item_url": "https://www.wowhead.com/tbc/item=34188/leggings-of-the-immortal-night",
          "rank_label": "Threat Skewed Alternative",
          "source_links": [
            {
              "href": "https://www.wowhead.com/tbc/npc=25038/felmyst",
              "text": "Felmyst"
            }
          ],
          "source_text": "Drop: Felmyst (Sunwell Plateau)"
        },
        {
          "cells": [
            "Alternative",
            "Thunderheart Leggings",
            "Drop: Leggings of the Forgotten Vanquisher - The Illidari Council (Black Temple)"
          ],
          "entities": [
            {
              "id": 31044,
              "name": "Thunderheart Leggings",
              "type": "item",
              "url": "https://www.wowhead.com/tbc/item=31044/thunderheart-leggings"
            }
          ],
          "entity_id": 31044,
          "entity_name": "Thunderheart Leggings",
          "entity_type": "item",
          "entity_url": "https://www.wowhead.com/tbc/item=31044/thunderheart-leggings",
          "item_id": 31044,
          "item_name": "Thunderheart Leggings",
          "item_url": "https://www.wowhead.com/tbc/item=31044/thunderheart-leggings",
          "rank_label": "Alternative",
          "source_links": [
            {
              "href": "https://www.wowhead.com/tbc/npc=23426/the-illidari-council",
              "text": "The Illidari Council"
            }
          ],
          "source_text": "Drop: Leggings of the Forgotten Vanquisher - The Illidari Council (Black Temple)"
        }
      ],
      "slot": "Legs"
    },
    {
      "data_family": "bis_lists",
      "heading": "Best in Slot Feet Armor for Feral Druid Tank in TBC Classic Phase 5",
      "rows": [
        {
          "cells": [
            "BiS",
            "Thunderheart Treads",
            "Drop: Boots of the Forgotten Vanquisher - Felmyst (Sunwell Plateau)"
          ],
          "entities": [
            {
              "id": 34573,
              "name": "Thunderheart Treads",
              "type": "item",
              "url": "https://www.wowhead.com/tbc/item=34573/thunderheart-treads"
            }
          ],
          "entity_id": 34573,
          "entity_name": "Thunderheart Treads",
          "entity_type": "item",
          "entity_url": "https://www.wowhead.com/tbc/item=34573/thunderheart-treads",
          "item_id": 34573,
          "item_name": "Thunderheart Treads",
          "item_url": "https://www.wowhead.com/tbc/item=34573/thunderheart-treads",
          "rank_label": "BiS",
          "source_links": [
            {
              "href": "https://www.wowhead.com/tbc/npc=25038/felmyst",
              "text": "Felmyst"
            }
          ],
          "source_text": "Drop: Boots of the Forgotten Vanquisher - Felmyst (Sunwell Plateau)"
        },
        {
          "cells": [
            "Alternative",
            "Treads of the Den Mother",
            "Zone Drop - Black Temple"
          ],
          "entities": [
            {
              "id": 32593,
              "name": "Treads of the Den Mother",
              "type": "item",
              "url": "https://www.wowhead.com/tbc/item=32593/treads-of-the-den-mother"
            }
          ],
          "entity_id": 32593,
          "entity_name": "Treads of the Den Mother",
          "entity_type": "item",
          "entity_url": "https://www.wowhead.com/tbc/item=32593/treads-of-the-den-mother",
          "item_id": 32593,
          "item_name": "Treads of the Den Mother",
          "item_url": "https://www.wowhead.com/tbc/item=32593/treads-of-the-den-mother",
          "rank_label": "Alternative",
          "source_links": [
            {
              "href": "https://www.wowhead.com/tbc/zone=3959/black-temple",
              "text": "Black Temple"
            }
          ],
          "source_text": "Zone Drop - Black Temple"
        },
        {
          "cells": [
            "Alternative",
            "Nyn'jah's Tabi Boots",
            "Vendor: G'eras (60 Badges of Justice)"
          ],
          "entities": [
            {
              "id": 33222,
              "name": "Nyn'jah's Tabi Boots",
              "type": "item",
              "url": "https://www.wowhead.com/tbc/item=33222/nynjahs-tabi-boots"
            }
          ],
          "entity_id": 33222,
          "entity_name": "Nyn'jah's Tabi Boots",
          "entity_type": "item",
          "entity_url": "https://www.wowhead.com/tbc/item=33222/nynjahs-tabi-boots",
          "item_id": 33222,
          "item_name": "Nyn'jah's Tabi Boots",
          "item_url": "https://www.wowhead.com/tbc/item=33222/nynjahs-tabi-boots",
          "rank_label": "Alternative",
          "source_links": [
            {
              "href": "https://www.wowhead.com/tbc/npc=18525/geras",
              "text": "G'eras"
            }
          ],
          "source_text": "Vendor: G'eras (60 Badges of Justice)"
        },
        {
          "cells": [
            "Alternative",
            "Guardian's Dragonhide Boots",
            "17,850 , 20 Eye of the Storm Mark of Honor , 1700 personal rating"
          ],
          "entities": [
            {
              "id": 35137,
              "name": "Guardian's Dragonhide Boots",
              "type": "item",
              "url": "https://www.wowhead.com/tbc/item=35137/guardians-dragonhide-boots"
            },
            {
              "id": 29024,
              "name": "Eye of the Storm Mark of Honor",
              "type": "item",
              "url": "https://www.wowhead.com/tbc/item=29024/eye-of-the-storm-mark-of-honor"
            }
          ],
          "entity_id": 35137,
          "entity_name": "Guardian's Dragonhide Boots",
          "entity_type": "item",
          "entity_url": "https://www.wowhead.com/tbc/item=35137/guardians-dragonhide-boots",
          "item_id": 35137,
          "item_name": "Guardian's Dragonhide Boots",
          "item_url": "https://www.wowhead.com/tbc/item=35137/guardians-dragonhide-boots",
          "rank_label": "Alternative",
          "source_links": [
            {
              "href": "https://www.wowhead.com/tbc/currency=1901",
              "text": ""
            },
            {
              "href": "https://www.wowhead.com/tbc/item=29024/eye-of-the-storm-mark-of-honor",
              "text": "Eye of the Storm Mark of Honor"
            }
          ],
          "source_text": "17,850 , 20 Eye of the Storm Mark of Honor , 1700 personal rating"
        }
      ],
      "slot": "Feet"
    },
    {
      "data_family": "bis_lists",
      "heading": "Best in Slot Feet Armor for Feral Druid Tank in TBC Classic Phase 5",
      "rows": [
        {
          "cells": [
            "Alternative",
            "Footwraps of Wild Encroachment",
            "Vendor: G'eras (60 Badges of Justice)"
          ],
          "entities": [
            {
              "id": 33582,
              "name": "Footwraps of Wild Encroachment",
              "type": "item",
              "url": "https://www.wowhead.com/tbc/item=33582/footwraps-of-wild-encroachment"
            }
          ],
          "entity_id": 33582,
          "entity_name": "Footwraps of Wild Encroachment",
          "entity_type": "item",
          "entity_url": "https://www.wowhead.com/tbc/item=33582/footwraps-of-wild-encroachment",
          "item_id": 33582,
          "item_name": "Footwraps of Wild Encroachment",
          "item_url": "https://www.wowhead.com/tbc/item=33582/footwraps-of-wild-encroachment",
          "rank_label": "Alternative",
          "source_links": [
            {
              "href": "https://www.wowhead.com/tbc/npc=18525/geras",
              "text": "G'eras"
            }
          ],
          "source_text": "Vendor: G'eras (60 Badges of Justice)"
        }
      ],
      "slot": "Feet"
    },
    {
      "data_family": "bis_lists",
      "heading": "Best in Slot Neck Jewelry for Feral Druid Tank in TBC Classic Phase 5",
      "rows": [
        {
          "cells": [
            "BiS",
            "Collar of the Pit Lord",
            "Drop: Brutallus (Sunwell Plateau)"
          ],
          "entities": [
            {
              "id": 34178,
              "name": "Collar of the Pit Lord",
              "type": "item",
              "url": "https://www.wowhead.com/tbc/item=34178/collar-of-the-pit-lord"
            }
          ],
          "entity_id": 34178,
          "entity_name": "Collar of the Pit Lord",
          "entity_type": "item",
          "entity_url": "https://www.wowhead.com/tbc/item=34178/collar-of-the-pit-lord",
          "item_id": 34178,
          "item_name": "Collar of the Pit Lord",
          "item_url": "https://www.wowhead.com/tbc/item=34178/collar-of-the-pit-lord",
          "rank_label": "BiS",
          "source_links": [
            {
              "href": "https://www.wowhead.com/tbc/npc=24882/brutallus",
              "text": "Brutallus"
            }
          ],
          "source_text": "Drop: Brutallus (Sunwell Plateau)"
        },
        {
          "cells": [
            "Mit Skewed Alternative",
            "Pendant of Titans",
            "Drop: Essence of Anger (Black Temple)"
          ],
          "entities": [
            {
              "id": 32362,
              "name": "Pendant of Titans",
              "type": "item",
              "url": "https://www.wowhead.com/tbc/item=32362/pendant-of-titans"
            }
          ],
          "entity_id": 32362,
          "entity_name": "Pendant of Titans",
          "entity_type": "item",
          "entity_url": "https://www.wowhead.com/tbc/item=32362/pendant-of-titans",
          "item_id": 32362,
          "item_name": "Pendant of Titans",
          "item_url": "https://www.wowhead.com/tbc/item=32362/pendant-of-titans",
          "rank_label": "Mit Skewed Alternative",
          "source_links": [
            {
              "href": "https://www.wowhead.com/tbc/npc=23420/essence-of-anger",
              "text": "Essence of Anger"
            }
          ],
          "source_text": "Drop: Essence of Anger (Black Temple)"
        },
        {
          "cells": [
            "Threat Skewed Alternative",
            "Brooch of Deftness",
            "Vendor: G'eras 35 Badges of Justice)"
          ],
          "entities": [
            {
              "id": 33296,
              "name": "Brooch of Deftness",
              "type": "item",
              "url": "https://www.wowhead.com/tbc/item=33296/brooch-of-deftness"
            }
          ],
          "entity_id": 33296,
          "entity_name": "Brooch of Deftness",
          "entity_type": "item",
          "entity_url": "https://www.wowhead.com/tbc/item=33296/brooch-of-deftness",
          "item_id": 33296,
          "item_name": "Brooch of Deftness",
          "item_url": "https://www.wowhead.com/tbc/item=33296/brooch-of-deftness",
          "rank_label": "Threat Skewed Alternative",
          "source_links": [
            {
              "href": "https://www.wowhead.com/tbc/npc=18525/geras",
              "text": "G'eras"
            }
          ],
          "source_text": "Vendor: G'eras 35 Badges of Justice)"
        },
        {
          "cells": [
            "Threat Skewed Alternative",
            "Hard Khorium Choker",
            "Profession: Jewelcrafting (BoP)"
          ],
          "entities": [
            {
              "id": 34358,
              "name": "Hard Khorium Choker",
              "type": "item",
              "url": "https://www.wowhead.com/tbc/item=34358/hard-khorium-choker"
            }
          ],
          "entity_id": 34358,
          "entity_name": "Hard Khorium Choker",
          "entity_type": "item",
          "entity_url": "https://www.wowhead.com/tbc/item=34358/hard-khorium-choker",
          "item_id": 34358,
          "item_name": "Hard Khorium Choker",
          "item_url": "https://www.wowhead.com/tbc/item=34358/hard-khorium-choker",
          "rank_label": "Threat Skewed Alternative",
          "source_links": [],
          "source_text": "Profession: Jewelcrafting (BoP)"
        }
      ],
      "slot": "Neck"
    },
    {
      "data_family": "bis_lists",
      "heading": "Best in Slot Ring Jewelry for Feral Druid Tank in TBC Classic Phase 5",
      "rows": [
        {
          "cells": [
            "Best Overall",
            "Ring of Hardened Resolve",
            "Drop: M'uru / Entropius (Sunwell Plateau)"
          ],
          "entities": [
            {
              "id": 34213,
              "name": "Ring of Hardened Resolve",
              "type": "item",
              "url": "https://www.wowhead.com/tbc/item=34213/ring-of-hardened-resolve"
            }
          ],
          "entity_id": 34213,
          "entity_name": "Ring of Hardened Resolve",
          "entity_type": "item",
          "entity_url": "https://www.wowhead.com/tbc/item=34213/ring-of-hardened-resolve",
          "item_id": 34213,
          "item_name": "Ring of Hardened Resolve",
          "item_url": "https://www.wowhead.com/tbc/item=34213/ring-of-hardened-resolve",
          "rank_label": "Best Overall",
          "source_links": [
            {
              "href": "https://www.wowhead.com/tbc/npc=25741/muru",
              "text": "M'uru"
            },
            {
              "href": "https://www.wowhead.com/tbc/npc=25840/entropius",
              "text": "Entropius"
            }
          ],
          "source_text": "Drop: M'uru / Entropius (Sunwell Plateau)"
        },
        {
          "cells": [
            "Best Below Armor Cap",
            "Ring of the Stalwart Protector",
            "Vendor: Smith Hauthaa - (60 Badges of Justice)"
          ],
          "entities": [
            {
              "id": 34888,
              "name": "Ring of the Stalwart Protector",
              "type": "item",
              "url": "https://www.wowhead.com/tbc/item=34888/ring-of-the-stalwart-protector"
            }
          ],
          "entity_id": 34888,
          "entity_name": "Ring of the Stalwart Protector",
          "entity_type": "item",
          "entity_url": "https://www.wowhead.com/tbc/item=34888/ring-of-the-stalwart-protector",
          "item_id": 34888,
          "item_name": "Ring of the Stalwart Protector",
          "item_url": "https://www.wowhead.com/tbc/item=34888/ring-of-the-stalwart-protector",
          "rank_label": "Best Below Armor Cap",
          "source_links": [
            {
              "href": "https://www.wowhead.com/tbc/npc=25046/smith-hauthaa",
              "text": "Smith Hauthaa"
            }
          ],
          "source_text": "Vendor: Smith Hauthaa - (60 Badges of Justice)"
        },
        {
          "cells": [
            "Best Above Armor Cap",
            "Hard Khorium Band",
            "Profession: Jewelcrafting (BoP)"
          ],
          "entities": [
            {
              "id": 34361,
              "name": "Hard Khorium Band",
              "type": "item",
              "url": "https://www.wowhead.com/tbc/item=34361/hard-khorium-band"
            }
          ],
          "entity_id": 34361,
          "entity_name": "Hard Khorium Band",
          "entity_type": "item",
          "entity_url": "https://www.wowhead.com/tbc/item=34361/hard-khorium-band",
          "item_id": 34361,
          "item_name": "Hard Khorium Band",
          "item_url": "https://www.wowhead.com/tbc/item=34361/hard-khorium-band",
          "rank_label": "Best Above Armor Cap",
          "source_links": [],
          "source_text": "Profession: Jewelcrafting (BoP)"
        },
        {
          "cells": [
            "Alternative (below Armor cap)",
            "Violet Signet of the Great Protector",
            "Quest: Path of the Violet Protector - Requires Exalted with The Violet Eye"
          ],
          "entities": [
            {
              "id": 29279,
              "name": "Violet Signet of the Great Protector",
              "type": "item",
              "url": "https://www.wowhead.com/tbc/item=29279/violet-signet-of-the-great-protector"
            }
          ],
          "entity_id": 29279,
          "entity_name": "Violet Signet of the Great Protector",
          "entity_type": "item",
          "entity_url": "https://www.wowhead.com/tbc/item=29279/violet-signet-of-the-great-protector",
          "item_id": 29279,
          "item_name": "Violet Signet of the Great Protector",
          "item_url": "https://www.wowhead.com/tbc/item=29279/violet-signet-of-the-great-protector",
          "rank_label": "Alternative (below Armor cap)",
          "source_links": [
            {
              "href": "https://www.wowhead.com/tbc/quest=10732/path-of-the-violet-protector",
              "text": "Path of the Violet Protector"
            }
          ],
          "source_text": "Quest: Path of the Violet Protector - Requires Exalted with The Violet Eye"
        }
      ],
      "slot": "Ring"
    },
    {
      "data_family": "bis_lists",
      "heading": "Best in Slot Ring Jewelry for Feral Druid Tank in TBC Classic Phase 5",
      "rows": [
        {
          "cells": [
            "Alternative (above Armor cap)",
            "Band of the Eternal Champion",
            "Quest: Champion's Covenant - Requires Exalted with Scale of the Sands"
          ],
          "entities": [
            {
              "id": 29301,
              "name": "Band of the Eternal Champion",
              "type": "item",
              "url": "https://www.wowhead.com/tbc/item=29301/band-of-the-eternal-champion"
            }
          ],
          "entity_id": 29301,
          "entity_name": "Band of the Eternal Champion",
          "entity_type": "item",
          "entity_url": "https://www.wowhead.com/tbc/item=29301/band-of-the-eternal-champion",
          "item_id": 29301,
          "item_name": "Band of the Eternal Champion",
          "item_url": "https://www.wowhead.com/tbc/item=29301/band-of-the-eternal-champion",
          "rank_label": "Alternative (above Armor cap)",
          "source_links": [
            {
              "href": "https://www.wowhead.com/tbc/quest=10474/champions-covenant",
              "text": "Champion's Covenant"
            }
          ],
          "source_text": "Quest: Champion's Covenant - Requires Exalted with Scale of the Sands"
        },
        {
          "cells": [
            "Alternative (above Armor cap)",
            "Ring of Deceitful Intent",
            "Drop: Shade of Akama (Black Temple)"
          ],
          "entities": [
            {
              "id": 32266,
              "name": "Ring of Deceitful Intent",
              "type": "item",
              "url": "https://www.wowhead.com/tbc/item=32266/ring-of-deceitful-intent"
            }
          ],
          "entity_id": 32266,
          "entity_name": "Ring of Deceitful Intent",
          "entity_type": "item",
          "entity_url": "https://www.wowhead.com/tbc/item=32266/ring-of-deceitful-intent",
          "item_id": 32266,
          "item_name": "Ring of Deceitful Intent",
          "item_url": "https://www.wowhead.com/tbc/item=32266/ring-of-deceitful-intent",
          "rank_label": "Alternative (above Armor cap)",
          "source_links": [
            {
              "href": "https://www.wowhead.com/tbc/npc=22841/shade-of-akama",
              "text": "Shade of Akama"
            }
          ],
          "source_text": "Drop: Shade of Akama (Black Temple)"
        }
      ],
      "slot": "Ring"
    },
    {
      "data_family": "bis_lists",
      "heading": "Best in Slot Trinkets for Feral Druid Tank in TBC Classic Phase 5",
      "rows": [
        {
          "cells": [
            "BiS",
            "Shadowmoon Insignia",
            "Drop: Gurtogg Bloodboil (Black Temple)"
          ],
          "entities": [
            {
              "id": 32501,
              "name": "Shadowmoon Insignia",
              "type": "item",
              "url": "https://www.wowhead.com/tbc/item=32501/shadowmoon-insignia"
            }
          ],
          "entity_id": 32501,
          "entity_name": "Shadowmoon Insignia",
          "entity_type": "item",
          "entity_url": "https://www.wowhead.com/tbc/item=32501/shadowmoon-insignia",
          "item_id": 32501,
          "item_name": "Shadowmoon Insignia",
          "item_url": "https://www.wowhead.com/tbc/item=32501/shadowmoon-insignia",
          "rank_label": "BiS",
          "source_links": [
            {
              "href": "https://www.wowhead.com/tbc/npc=22948/gurtogg-bloodboil",
              "text": "Gurtogg Bloodboil"
            }
          ],
          "source_text": "Drop: Gurtogg Bloodboil (Black Temple)"
        },
        {
          "cells": [
            "BiS",
            "Badge of Tenacity",
            "Depleted Badge , 50 Apexis Shard (Blades Edge Mountains)"
          ],
          "entities": [
            {
              "id": 32658,
              "name": "Badge of Tenacity",
              "type": "item",
              "url": "https://www.wowhead.com/tbc/item=32658/badge-of-tenacity"
            },
            {
              "id": 32672,
              "name": "Depleted Badge",
              "type": "item",
              "url": "https://www.wowhead.com/tbc/item=32672/depleted-badge"
            },
            {
              "id": 32569,
              "name": "Apexis Shard",
              "type": "item",
              "url": "https://www.wowhead.com/tbc/item=32569/apexis-shard"
            }
          ],
          "entity_id": 32658,
          "entity_name": "Badge of Tenacity",
          "entity_type": "item",
          "entity_url": "https://www.wowhead.com/tbc/item=32658/badge-of-tenacity",
          "item_id": 32658,
          "item_name": "Badge of Tenacity",
          "item_url": "https://www.wowhead.com/tbc/item=32658/badge-of-tenacity",
          "rank_label": "BiS",
          "source_links": [
            {
              "href": "https://www.wowhead.com/tbc/item=32672/depleted-badge",
              "text": "Depleted Badge"
            },
            {
              "href": "https://www.wowhead.com/tbc/item=32569/apexis-shard",
              "text": "Apexis Shard"
            }
          ],
          "source_text": "Depleted Badge , 50 Apexis Shard (Blades Edge Mountains)"
        },
        {
          "cells": [
            "Alternative",
            "Commendation of Kael'thas",
            "Drop: Priestess Delrissa (Heroic Magisters' Terrace)"
          ],
          "entities": [
            {
              "id": 34473,
              "name": "Commendation of Kael'thas",
              "type": "item",
              "url": "https://www.wowhead.com/tbc/item=34473/commendation-of-kaelthas"
            }
          ],
          "entity_id": 34473,
          "entity_name": "Commendation of Kael'thas",
          "entity_type": "item",
          "entity_url": "https://www.wowhead.com/tbc/item=34473/commendation-of-kaelthas",
          "item_id": 34473,
          "item_name": "Commendation of Kael'thas",
          "item_url": "https://www.wowhead.com/tbc/item=34473/commendation-of-kaelthas",
          "rank_label": "Alternative",
          "source_links": [
            {
              "href": "https://www.wowhead.com/tbc/npc=24560/priestess-delrissa",
              "text": "Priestess Delrissa"
            }
          ],
          "source_text": "Drop: Priestess Delrissa (Heroic Magisters' Terrace)"
        },
        {
          "cells": [
            "Alternative",
            "Moroes' Lucky Pocket Watch",
            "Drop: Moroes (Karazhan)"
          ],
          "entities": [
            {
              "id": 28528,
              "name": "Moroes' Lucky Pocket Watch",
              "type": "item",
              "url": "https://www.wowhead.com/tbc/item=28528/moroes-lucky-pocket-watch"
            }
          ],
          "entity_id": 28528,
          "entity_name": "Moroes' Lucky Pocket Watch",
          "entity_type": "item",
          "entity_url": "https://www.wowhead.com/tbc/item=28528/moroes-lucky-pocket-watch",
          "item_id": 28528,
          "item_name": "Moroes' Lucky Pocket Watch",
          "item_url": "https://www.wowhead.com/tbc/item=28528/moroes-lucky-pocket-watch",
          "rank_label": "Alternative",
          "source_links": [
            {
              "href": "https://www.wowhead.com/tbc/npc=15687/moroes",
              "text": "Moroes"
            }
          ],
          "source_text": "Drop: Moroes (Karazhan)"
        }
      ],
      "slot": "Trinket"
    },
    {
      "data_family": "bis_lists",
      "heading": "Best in Slot Trinkets for Feral Druid Tank in TBC Classic Phase 5",
      "rows": [
        {
          "cells": [
            "Alternative",
            "Steely Naaru Sliver",
            "Drop: M'uru / Entropius (Sunwell Plateau)]"
          ],
          "entities": [
            {
              "id": 34428,
              "name": "Steely Naaru Sliver",
              "type": "item",
              "url": "https://www.wowhead.com/tbc/item=34428/steely-naaru-sliver"
            }
          ],
          "entity_id": 34428,
          "entity_name": "Steely Naaru Sliver",
          "entity_type": "item",
          "entity_url": "https://www.wowhead.com/tbc/item=34428/steely-naaru-sliver",
          "item_id": 34428,
          "item_name": "Steely Naaru Sliver",
          "item_url": "https://www.wowhead.com/tbc/item=34428/steely-naaru-sliver",
          "rank_label": "Alternative",
          "source_links": [
            {
              "href": "https://www.wowhead.com/tbc/npc=25741/muru",
              "text": "M'uru"
            },
            {
              "href": "https://www.wowhead.com/tbc/npc=25840/entropius",
              "text": "Entropius"
            }
          ],
          "source_text": "Drop: M'uru / Entropius (Sunwell Plateau)]"
        },
        {
          "cells": [
            "Alternative",
            "Battlemaster's Determination",
            "30,000 , 20 Alterac Valley Mark of Honor or 75 Badge of Justice"
          ],
          "entities": [
            {
              "id": 34578,
              "name": "Battlemaster's Determination",
              "type": "item",
              "url": "https://www.wowhead.com/tbc/item=34578/battlemasters-determination"
            },
            {
              "id": 20560,
              "name": "Alterac Valley Mark of Honor",
              "type": "item",
              "url": "https://www.wowhead.com/tbc/item=20560/alterac-valley-mark-of-honor"
            },
            {
              "id": 29434,
              "name": "Badge of Justice",
              "type": "item",
              "url": "https://www.wowhead.com/tbc/item=29434/badge-of-justice"
            }
          ],
          "entity_id": 34578,
          "entity_name": "Battlemaster's Determination",
          "entity_type": "item",
          "entity_url": "https://www.wowhead.com/tbc/item=34578/battlemasters-determination",
          "item_id": 34578,
          "item_name": "Battlemaster's Determination",
          "item_url": "https://www.wowhead.com/tbc/item=34578/battlemasters-determination",
          "rank_label": "Alternative",
          "source_links": [
            {
              "href": "https://www.wowhead.com/tbc/currency=1901",
              "text": ""
            },
            {
              "href": "https://www.wowhead.com/tbc/item=20560/alterac-valley-mark-of-honor",
              "text": "Alterac Valley Mark of Honor"
            },
            {
              "href": "https://www.wowhead.com/tbc/item=29434/badge-of-justice",
              "text": "Badge of Justice"
            }
          ],
          "source_text": "30,000 , 20 Alterac Valley Mark of Honor or 75 Badge of Justice"
        },
        {
          "cells": [
            "Alternative",
            "Battlemaster's Cruelty",
            "30,000 , 20 Alterac Valley Mark of Honor or 75 Badge of Justice"
          ],
          "entities": [
            {
              "id": 34576,
              "name": "Battlemaster's Cruelty",
              "type": "item",
              "url": "https://www.wowhead.com/tbc/item=34576/battlemasters-cruelty"
            },
            {
              "id": 20560,
              "name": "Alterac Valley Mark of Honor",
              "type": "item",
              "url": "https://www.wowhead.com/tbc/item=20560/alterac-valley-mark-of-honor"
            },
            {
              "id": 29434,
              "name": "Badge of Justice",
              "type": "item",
              "url": "https://www.wowhead.com/tbc/item=29434/badge-of-justice"
            }
          ],
          "entity_id": 34576,
          "entity_name": "Battlemaster's Cruelty",
          "entity_type": "item",
          "entity_url": "https://www.wowhead.com/tbc/item=34576/battlemasters-cruelty",
          "item_id": 34576,
          "item_name": "Battlemaster's Cruelty",
          "item_url": "https://www.wowhead.com/tbc/item=34576/battlemasters-cruelty",
          "rank_label": "Alternative",
          "source_links": [
            {
              "href": "https://www.wowhead.com/tbc/currency=1901",
              "text": ""
            },
            {
              "href": "https://www.wowhead.com/tbc/item=20560/alterac-valley-mark-of-honor",
              "text": "Alterac Valley Mark of Honor"
            },
            {
              "href": "https://www.wowhead.com/tbc/item=29434/badge-of-justice",
              "text": "Badge of Justice"
            }
          ],
          "source_text": "30,000 , 20 Alterac Valley Mark of Honor or 75 Badge of Justice"
        },
        {
          "cells": [
            "Alternative",
            "Shard of Contempt",
            "Drop: Priestess Delrissa (Heroic Magisters' Terrace)"
          ],
          "entities": [
            {
              "id": 34472,
              "name": "Shard of Contempt",
              "type": "item",
              "url": "https://www.wowhead.com/tbc/item=34472/shard-of-contempt"
            }
          ],
          "entity_id": 34472,
          "entity_name": "Shard of Contempt",
          "entity_type": "item",
          "entity_url": "https://www.wowhead.com/tbc/item=34472/shard-of-contempt",
          "item_id": 34472,
          "item_name": "Shard of Contempt",
          "item_url": "https://www.wowhead.com/tbc/item=34472/shard-of-contempt",
          "rank_label": "Alternative",
          "source_links": [
            {
              "href": "https://www.wowhead.com/tbc/npc=24560/priestess-delrissa",
              "text": "Priestess Delrissa"
            }
          ],
          "source_text": "Drop: Priestess Delrissa (Heroic Magisters' Terrace)"
        },
        {
          "cells": [
            "Alternative",
            "Darkmoon Card: Vengeance",
            "Quest: Darkmoon Furies Deck"
          ],
          "entities": [
            {
              "id": 31858,
              "name": "Darkmoon Card: Vengeance",
              "type": "item",
              "url": "https://www.wowhead.com/tbc/item=31858/darkmoon-card-vengeance"
            }
          ],
          "entity_id": 31858,
          "entity_name": "Darkmoon Card: Vengeance",
          "entity_type": "item",
          "entity_url": "https://www.wowhead.com/tbc/item=31858/darkmoon-card-vengeance",
          "item_id": 31858,
          "item_name": "Darkmoon Card: Vengeance",
          "item_url": "https://www.wowhead.com/tbc/item=31858/darkmoon-card-vengeance",
          "rank_label": "Alternative",
          "source_links": [
            {
              "href": "https://www.wowhead.com/tbc/quest=10940/darkmoon-furies-deck",
              "text": "Darkmoon Furies Deck"
            }
          ],
          "source_text": "Quest: Darkmoon Furies Deck"
        }
      ],
      "slot": "Trinket"
    },
    {
      "data_family": "unknown",
      "heading": "Best in Slot Weapons for Feral Druid Tank in TBC Classic Phase 5",
      "rows": [
        {
          "cells": [
            "Best Mit Skewed",
            "Pillar of Ferocity",
            "Drop: Anetheron (Hyjal Summit)"
          ],
          "entities": [
            {
              "id": 30883,
              "name": "Pillar of Ferocity",
              "type": "item",
              "url": "https://www.wowhead.com/tbc/item=30883/pillar-of-ferocity"
            }
          ],
          "entity_id": 30883,
          "entity_name": "Pillar of Ferocity",
          "entity_type": "item",
          "entity_url": "https://www.wowhead.com/tbc/item=30883/pillar-of-ferocity",
          "item_id": 30883,
          "item_name": "Pillar of Ferocity",
          "item_url": "https://www.wowhead.com/tbc/item=30883/pillar-of-ferocity",
          "rank_label": "Best Mit Skewed",
          "source_links": [
            {
              "href": "https://www.wowhead.com/tbc/npc=17808/anetheron",
              "text": "Anetheron"
            }
          ],
          "source_text": "Drop: Anetheron (Hyjal Summit)"
        },
        {
          "cells": [
            "Best Threat Skewed",
            "Stanchion of Primal Instinct",
            "Drop: Grand Warlock Alythess / Lady Sacrolash (Sunwell Plateau)"
          ],
          "entities": [
            {
              "id": 34198,
              "name": "Stanchion of Primal Instinct",
              "type": "item",
              "url": "https://www.wowhead.com/tbc/item=34198/stanchion-of-primal-instinct"
            }
          ],
          "entity_id": 34198,
          "entity_name": "Stanchion of Primal Instinct",
          "entity_type": "item",
          "entity_url": "https://www.wowhead.com/tbc/item=34198/stanchion-of-primal-instinct",
          "item_id": 34198,
          "item_name": "Stanchion of Primal Instinct",
          "item_url": "https://www.wowhead.com/tbc/item=34198/stanchion-of-primal-instinct",
          "rank_label": "Best Threat Skewed",
          "source_links": [
            {
              "href": "https://www.wowhead.com/tbc/npc=25166/grand-warlock-alythess",
              "text": "Grand Warlock Alythess"
            },
            {
              "href": "https://www.wowhead.com/tbc/npc=25165/lady-sacrolash",
              "text": "Lady Sacrolash"
            }
          ],
          "source_text": "Drop: Grand Warlock Alythess / Lady Sacrolash (Sunwell Plateau)"
        },
        {
          "cells": [
            "Mit Skewed Alternative",
            "Wildfury Greatstaff",
            "Zone Drop - Serpentshrine Cavern"
          ],
          "entities": [
            {
              "id": 30021,
              "name": "Wildfury Greatstaff",
              "type": "item",
              "url": "https://www.wowhead.com/tbc/item=30021/wildfury-greatstaff"
            }
          ],
          "entity_id": 30021,
          "entity_name": "Wildfury Greatstaff",
          "entity_type": "item",
          "entity_url": "https://www.wowhead.com/tbc/item=30021/wildfury-greatstaff",
          "item_id": 30021,
          "item_name": "Wildfury Greatstaff",
          "item_url": "https://www.wowhead.com/tbc/item=30021/wildfury-greatstaff",
          "rank_label": "Mit Skewed Alternative",
          "source_links": [
            {
              "href": "https://www.wowhead.com/tbc/zone=3607/serpentshrine-cavern",
              "text": "Serpentshrine Cavern"
            }
          ],
          "source_text": "Zone Drop - Serpentshrine Cavern"
        },
        {
          "cells": [
            "Threat Skewed Alternative",
            "Brutal Gladiator's Staff",
            "Drop: Serpentshrine Cavern Trash Mobs"
          ],
          "entities": [
            {
              "id": 35103,
              "name": "Brutal Gladiator's Staff",
              "type": "item",
              "url": "https://www.wowhead.com/tbc/item=35103/brutal-gladiators-staff"
            }
          ],
          "entity_id": 35103,
          "entity_name": "Brutal Gladiator's Staff",
          "entity_type": "item",
          "entity_url": "https://www.wowhead.com/tbc/item=35103/brutal-gladiators-staff",
          "item_id": 35103,
          "item_name": "Brutal Gladiator's Staff",
          "item_url": "https://www.wowhead.com/tbc/item=35103/brutal-gladiators-staff",
          "rank_label": "Threat Skewed Alternative",
          "source_links": [
            {
              "href": "https://www.wowhead.com/tbc/zone=3607/serpentshrine-cavern",
              "text": "Serpentshrine Cavern"
            }
          ],
          "source_text": "Drop: Serpentshrine Cavern Trash Mobs"
        }
      ],
      "slot": null
    },
    {
      "data_family": "unknown",
      "heading": "Best in Slot Weapons for Feral Druid Tank in TBC Classic Phase 5",
      "rows": [
        {
          "cells": [
            "Threat Skewed Alternative",
            "Staff of the Forest Lord",
            "Vendor: Smith Hauthaa (150 Badges of Justice)"
          ],
          "entities": [
            {
              "id": 34898,
              "name": "Staff of the Forest Lord",
              "type": "item",
              "url": "https://www.wowhead.com/tbc/item=34898/staff-of-the-forest-lord"
            }
          ],
          "entity_id": 34898,
          "entity_name": "Staff of the Forest Lord",
          "entity_type": "item",
          "entity_url": "https://www.wowhead.com/tbc/item=34898/staff-of-the-forest-lord",
          "item_id": 34898,
          "item_name": "Staff of the Forest Lord",
          "item_url": "https://www.wowhead.com/tbc/item=34898/staff-of-the-forest-lord",
          "rank_label": "Threat Skewed Alternative",
          "source_links": [
            {
              "href": "https://www.wowhead.com/tbc/npc=25046/smith-hauthaa",
              "text": "Smith Hauthaa"
            }
          ],
          "source_text": "Vendor: Smith Hauthaa (150 Badges of Justice)"
        }
      ],
      "slot": null
    },
    {
      "data_family": "bis_lists",
      "heading": "Idols for Feral Druid Tank in Phase 5",
      "rows": [
        {
          "cells": [
            "Best Individually",
            "Idol of Terror",
            "Vendor: G'eras (20 Badges of Justice)"
          ],
          "entities": [
            {
              "id": 33509,
              "name": "Idol of Terror",
              "type": "item",
              "url": "https://www.wowhead.com/tbc/item=33509/idol-of-terror"
            }
          ],
          "entity_id": 33509,
          "entity_name": "Idol of Terror",
          "entity_type": "item",
          "entity_url": "https://www.wowhead.com/tbc/item=33509/idol-of-terror",
          "item_id": 33509,
          "item_name": "Idol of Terror",
          "item_url": "https://www.wowhead.com/tbc/item=33509/idol-of-terror",
          "rank_label": "Best Individually",
          "source_links": [
            {
              "href": "https://www.wowhead.com/tbc/npc=18525/geras",
              "text": "G'eras"
            }
          ],
          "source_text": "Vendor: G'eras (20 Badges of Justice)"
        },
        {
          "cells": [
            "Best for Raid DPS",
            "Idol of the Raven Goddess",
            "Quest: Vanquish the Raven God"
          ],
          "entities": [
            {
              "id": 32387,
              "name": "Idol of the Raven Goddess",
              "type": "item",
              "url": "https://www.wowhead.com/tbc/item=32387/idol-of-the-raven-goddess"
            }
          ],
          "entity_id": 32387,
          "entity_name": "Idol of the Raven Goddess",
          "entity_type": "item",
          "entity_url": "https://www.wowhead.com/tbc/item=32387/idol-of-the-raven-goddess",
          "item_id": 32387,
          "item_name": "Idol of the Raven Goddess",
          "item_url": "https://www.wowhead.com/tbc/item=32387/idol-of-the-raven-goddess",
          "rank_label": "Best for Raid DPS",
          "source_links": [
            {
              "href": "https://www.wowhead.com/tbc/quest=11001/vanquish-the-raven-god",
              "text": "Vanquish the Raven God"
            }
          ],
          "source_text": "Quest: Vanquish the Raven God"
        },
        {
          "cells": [
            "Best for Personal TPS",
            "Idol of the White Stag",
            "Drop: Supremus (Black Temple)"
          ],
          "entities": [
            {
              "id": 32257,
              "name": "Idol of the White Stag",
              "type": "item",
              "url": "https://www.wowhead.com/tbc/item=32257/idol-of-the-white-stag"
            }
          ],
          "entity_id": 32257,
          "entity_name": "Idol of the White Stag",
          "entity_type": "item",
          "entity_url": "https://www.wowhead.com/tbc/item=32257/idol-of-the-white-stag",
          "item_id": 32257,
          "item_name": "Idol of the White Stag",
          "item_url": "https://www.wowhead.com/tbc/item=32257/idol-of-the-white-stag",
          "rank_label": "Best for Personal TPS",
          "source_links": [
            {
              "href": "https://www.wowhead.com/tbc/npc=22898/supremus",
              "text": "Supremus"
            }
          ],
          "source_text": "Drop: Supremus (Black Temple)"
        },
        {
          "cells": [
            "Alternative",
            "Idol of Brutality",
            "Drop: Magistrate Barthilas (Stratholme)"
          ],
          "entities": [
            {
              "id": 23198,
              "name": "Idol of Brutality",
              "type": "item",
              "url": "https://www.wowhead.com/tbc/item=23198/idol-of-brutality"
            }
          ],
          "entity_id": 23198,
          "entity_name": "Idol of Brutality",
          "entity_type": "item",
          "entity_url": "https://www.wowhead.com/tbc/item=23198/idol-of-brutality",
          "item_id": 23198,
          "item_name": "Idol of Brutality",
          "item_url": "https://www.wowhead.com/tbc/item=23198/idol-of-brutality",
          "rank_label": "Alternative",
          "source_links": [
            {
              "href": "https://www.wowhead.com/tbc/npc=10435/magistrate-barthilas",
              "text": "Magistrate Barthilas"
            }
          ],
          "source_text": "Drop: Magistrate Barthilas (Stratholme)"
        }
      ],
      "slot": "Idol"
    },
    {
      "data_family": "bis_lists",
      "heading": "Idols for Feral Druid Tank in Phase 5",
      "rows": [
        {
          "cells": [
            "Alternative",
            "Idol of the Wild",
            "Quest: Colossal Menace"
          ],
          "entities": [
            {
              "id": 28064,
              "name": "Idol of the Wild",
              "type": "item",
              "url": "https://www.wowhead.com/tbc/item=28064/idol-of-the-wild"
            }
          ],
          "entity_id": 28064,
          "entity_name": "Idol of the Wild",
          "entity_type": "item",
          "entity_url": "https://www.wowhead.com/tbc/item=28064/idol-of-the-wild",
          "item_id": 28064,
          "item_name": "Idol of the Wild",
          "item_url": "https://www.wowhead.com/tbc/item=28064/idol-of-the-wild",
          "rank_label": "Alternative",
          "source_links": [
            {
              "href": "https://www.wowhead.com/tbc/quest=10132/colossal-menace",
              "text": "Colossal Menace"
            }
          ],
          "source_text": "Quest: Colossal Menace"
        },
        {
          "cells": [
            "Alternative",
            "Idol of Ursoc",
            "Drop: Hungarfen (Heroic The Underbog)"
          ],
          "entities": [
            {
              "id": 27744,
              "name": "Idol of Ursoc",
              "type": "item",
              "url": "https://www.wowhead.com/tbc/item=27744/idol-of-ursoc"
            }
          ],
          "entity_id": 27744,
          "entity_name": "Idol of Ursoc",
          "entity_type": "item",
          "entity_url": "https://www.wowhead.com/tbc/item=27744/idol-of-ursoc",
          "item_id": 27744,
          "item_name": "Idol of Ursoc",
          "item_url": "https://www.wowhead.com/tbc/item=27744/idol-of-ursoc",
          "rank_label": "Alternative",
          "source_links": [
            {
              "href": "https://www.wowhead.com/tbc/npc=17770/hungarfen",
              "text": "Hungarfen"
            }
          ],
          "source_text": "Drop: Hungarfen (Heroic The Underbog)"
        }
      ],
      "slot": "Idol"
    }
  ],
  "title": "Burning Crusade Classic Feral Druid Tank Best in Slot (BiS) Phase 5 Gear Guide - Wowhead",
  "url": "https://www.wowhead.com/tbc/guide/feral-druid-tank-swp-phase-5-best-in-slot-gear-burning-crusade"
}
