{
  "binding": "bind_on_pickup",
  "boe": false,
  "description": "This epic amulet of item level 141 goes in the \"Neck\" slot. It is looted from Supremus. In the Amulets category. Added in World of Warcraft: The Burning Crusade.",
  "fetched_at": "2026-05-24T04:37:39+00:00",
  "item_id": 32260,
  "name": "Choker of Endless Nightmares",
  "normalized_sources": [
    {
      "confidence": "wowhead_item",
      "count": 33,
      "drop_percent": 9.27,
      "entity_id": 22898,
      "entity_name": "Supremus",
      "out_of": 356,
      "source_url": "https://www.wowhead.com/tbc/item=32260/choker-of-endless-nightmares",
      "type": "drop",
      "zone": "Black Temple"
    }
  ],
  "page_type": "item",
  "parser_version": "wowhead-scraper-0.4.0",
  "quality": "epic",
  "related_tables": {
    "created-by": [],
    "dropped-by": [
      {
        "boss": 1,
        "classification": 3,
        "count": 33,
        "id": 22898,
        "itemSeasonPhaseData": {
          "0": {
            "0": {
              "0": {
                "count": 100,
                "outof": 566
              }
            },
            "4": {
              "0": {
                "count": 33,
                "outof": 356
              }
            },
            "5": {
              "0": {
                "count": 74,
                "outof": 528
              }
            }
          }
        },
        "location": [
          3959
        ],
        "modes": {
          "0": {
            "count": 100,
            "outof": 566
          },
          "mode": [
            0
          ]
        },
        "name": "Supremus",
        "outof": 356,
        "pctstack": null,
        "personal_loot": 0,
        "react": [
          -1,
          -1
        ],
        "type": 3
      }
    ],
    "reward-from-q": [],
    "sold-by": []
  },
  "url": "https://www.wowhead.com/tbc/item=32260/choker-of-endless-nightmares"
}
